ssie/__init__.py
ssie/parse_nested_dict.py
ssie/ssie.py
ssie-0.0.4.dist-info/licenses/LICENSE
ssie-0.0.4.dist-info/METADATA
ssie-0.0.4.dist-info/WHEEL
ssie-0.0.4.dist-info/top_level.txt
ssie-0.0.4.dist-info/RECORD
